HISTORY.rst
MANIFEST.in
README.md
README.rst
setup.py
bts_tools/__init__.py
bts_tools/backbone.py
bts_tools/base58.py
bts_tools/cmdline.py
bts_tools/config.yaml
bts_tools/core.py
bts_tools/deploy.py
bts_tools/feeds.py
bts_tools/frontend.py
bts_tools/graphene.py
bts_tools/monitor.py
bts_tools/network_utils.py
bts_tools/notification.py
bts_tools/privatekey.py
bts_tools/process.py
bts_tools/repl.py
bts_tools/rpcutils.py
bts_tools/seednodes.py
bts_tools/slate.yaml
bts_tools/slogging.py
bts_tools/version.txt
bts_tools/views.py
bts_tools/wsgi.py
bts_tools/wsgi_status_bts.py
bts_tools/wsgi_status_muse.py
bts_tools/wsgi_status_ppy.py
bts_tools/wsgi_status_steem.py
bts_tools.egg-info/PKG-INFO
bts_tools.egg-info/SOURCES.txt
bts_tools.egg-info/dependency_links.txt
bts_tools.egg-info/entry_points.txt
bts_tools.egg-info/requires.txt
bts_tools.egg-info/top_level.txt
bts_tools/commands/__init__.py
bts_tools/commands/install_boost.py
bts_tools/commands/truncate.py
bts_tools/feed_providers/__init__.py
bts_tools/feed_providers/aex.py
bts_tools/feed_providers/binance.py
bts_tools/feed_providers/bitcoinaverage.py
bts_tools/feed_providers/bitfinex.py
bts_tools/feed_providers/bitstamp.py
bts_tools/feed_providers/bittrex.py
bts_tools/feed_providers/bloomberg.py
bts_tools/feed_providers/btc38.py
bts_tools/feed_providers/bter.py
bts_tools/feed_providers/coincap.py
bts_tools/feed_providers/coinmarketcap.py
bts_tools/feed_providers/currencylayer.py
bts_tools/feed_providers/fixer.py
bts_tools/feed_providers/livecoin.py
bts_tools/feed_providers/poloniex.py
bts_tools/feed_providers/quandl.py
bts_tools/feed_providers/uphold.py
bts_tools/feed_providers/yunbi.py
bts_tools/feed_providers/zb.py
bts_tools/monitoring/__init__.py
bts_tools/monitoring/backbone.py
bts_tools/monitoring/cpu_ram_usage.py
bts_tools/monitoring/fork.py
bts_tools/monitoring/free_disk_space.py
bts_tools/monitoring/indexing.py
bts_tools/monitoring/missed.py
bts_tools/monitoring/network_connections.py
bts_tools/monitoring/online.py
bts_tools/monitoring/prefer_backbone_exclusively.py
bts_tools/monitoring/seed.py
bts_tools/monitoring/voted_in.py
bts_tools/monitoring/wallet_state.py
bts_tools/static/.DS_Store
