Metadata-Version: 1.1
Name: bts-tools
Version: 0.5.2
Summary: Graphene blockchains management tools
Home-page: https://github.com/wackou/bts_tools
Author: Nicolas Wack
Author-email: wackou@gmail.com
License: UNKNOWN
Keywords: Graphene blockchain witness management tools bitshares steem peerplays muse
Platform: UNKNOWN
Classifier: Development Status :: 4 - Beta
Classifier: License :: OSI Approved :: GNU General Public License v3 or later (GPLv3+)
Classifier: Operating System :: OS Independent
Classifier: Programming Language :: Python :: 3
Classifier: Programming Language :: Python :: 3.4
